{"data_id":"1047100","Date":"2020-10-30 15:08:50","calendar_enabled":"1","remote_start_enabled":"","vehicle_id":"934443942","display_name":"DebugCar","color":"","fast_charger_brand":"<invalid>","notifications_enabled":"","vin":"5YJ3E1EA5JF154213","conn_charge_cable":"SAE","id":"27207980592358211","charge_port_cold_weather_mode":"0","id_s":"","state":"online","option_codes":"AD15,MDL3,PBSB,RENA,BT37,ID3W,RF3G,S3PB,DRLH,DV2W,","user_charge_enable_request":"1","time_to_full_charge":"8.92","charge_current_request":"5","charge_enable_request":"1","charge_to_max_range":"1","charger_phases":"1","battery_heater_on":"0","managed_charging_start_time":"","battery_range":"197.97","charger_power":"1","charge_limit_soc":"95","charger_pilot_current":"32","charge_port_latch":"Engaged","battery_current":"","charger_actual_current":"5","scheduled_charging_pending":"0","fast_charger_type":"MCSingleWireCAN","usable_battery_level":"79","motorized_charge_port":"1","charge_limit_soc_std":"90","not_enough_power_to_heat":"","battery_level":"79","charge_energy_added":"26.08","charge_port_door_open":"1","max_range_charge_counter":"0","charge_limit_soc_max":"100","ideal_battery_range":"197.97","managed_charging_active":"0","charging_state":"Charging","fast_charger_present":"0","trip_charging":"0","managed_charging_user_canceled":"0","scheduled_charging_start_time":"","est_battery_range":"167.62","charge_rate":"4.3","charger_voltage":"241","charge_current_request_max":"32","eu_vehicle":"0","charge_miles_added_ideal":"110.5","charge_limit_soc_min":"50","charge_miles_added_rated":"110.5","inside_temp":"15.3","longitude":"-72.721865","heading":"18","gps_as_of":"1604084925","latitude":"41.638919","speed":"","shift_state":"","seat_heater_rear_right":"0","seat_heater_rear_left_back":"","seat_heater_left":"0","passenger_temp_setting":"23.3","is_auto_conditioning_on":"0","driver_temp_setting":"23.3","outside_temp":"13.0","seat_heater_rear_center":"0","is_rear_defroster_on":"0","seat_heater_rear_right_back":"","smart_preconditioning":"","seat_heater_right":"0","fan_status":"0","is_front_defroster_on":"0","seat_heater_rear_left":"0","gui_charge_rate_units":"","gui_24_hour_time":"","gui_temperature_units":"","gui_range_display":"","gui_distance_units":"","sun_roof_installed":"","rhd":"0","remote_start_supported":"1","homelink_nearby":"1","parsed_calendar_supported":"1","spoiler_type":"None","ft":"0","odometer":"14876.744896","remote_start":"0","pr":"0","climate_keeper_mode":"off","roof_color":"Glass","perf_config":"","valet_mode":"0","calendar_supported":"1","pf":"0","sun_roof_percent_open":"","third_row_seats":"<invalid>","seat_type":"","api_version":"10","rear_seat_heaters":"1","rt":"0","exterior_color":"DeepBlue","df":"0","autopark_state":"unavailable","sun_roof_state":"","notifications_supported":"1","vehicle_name":"DebugCar","dr":"0","autopark_style":"","car_type":"model","wheel_type":"Pinwheel18","locked":"1","center_display_state":"0","last_autopark_error":"","car_version":"2020.40.8 9744d0c0d3","defrost_mode":"0","autopark_state_v2":"","is_preconditioning":"0","inside_tempF":"59","driver_temp_settingF":"73","outside_tempF":"55","battery_heater":"","Notes":"Idling->Charging","odometerF":"None","idleNumber":"4681","sleepNumber":"0","driveNumber":"0","chargeNumber":"416","polling":"","idleTime":"0","maxRange":"249.48","left_temp_direction":"0","max_avail_temp":"28.0","is_climate_on":"0","right_temp_direction":"0","min_avail_temp":"15.0","is_user_present":"0","in_service":"0","valet_pin_needed":"","charge_port_led_color":"","timestamp":"","power":"-1","side_mirror_heaters":"","wiper_blade_heater":"","steering_wheel_heater":"","elevation":"","sentry_mode":"0","fd_window":"0","fp_window":"0","rd_window":"0","rp_window":"0","measure":"imperial","temperature":"F","currency":"$","carState":"Charging","location":"Home","rangeDisplay":"rated","newVersion":"","newVersionStatus":""}